sqltree/__init__.py
sqltree/__main__.py
sqltree/api.py
sqltree/dialect.py
sqltree/fixit.py
sqltree/formatter.py
sqltree/keywords.py
sqltree/location.py
sqltree/mangler.py
sqltree/parser.py
sqltree/peeking_iterator.py
sqltree/tokenizer.py
sqltree/tools.py
sqltree/visitor.py
sqltree-0.3.0.dist-info/LICENSE
sqltree-0.3.0.dist-info/WHEEL
sqltree-0.3.0.dist-info/METADATA
sqltree-0.3.0.dist-info/RECORD
