Metadata-Version: 2.1
Name: sqltree
Version: 0.3.0
Summary: A SQL parser.
Author-email: Jelle Zijlstra <jelle.zijlstra@gmail.com>
Classifier: License :: OSI Approved :: Apache Software License
Project-URL: Home, https://github.com/JelleZijlstra/sqltree
